{"authors.": {"authors": ["Thomas Mueller", "Georg Ehrke", "Bart Visscher", "Robin Appelman", "Lukas Reschke", "J\u00f6rn Friedrich Dreyer", "Morris Jobke", "Michael Gapczynski", "Thomas Tanghus", "Bj\u00f6rn Schie\u00dfle"], "commits": [59, 36, 35, 35, 32, 16, 11, 10, 10, 9], "id": [22, 27, 33, 45, 16, 34, 18, 146, 148, 32]}, "authors.last month": {"authors": ["Morris Jobke", "Thomas Mueller", "Andreas Fischer", "Remco Brenninkmeijer"], "commits": [7, 3, 2, 1], "id": [18, 22, 366, 466]}, "authors.last year": {"authors": ["Thomas Mueller", "Lukas Reschke", "Morris Jobke", "Georg Ehrke", "Vincent Petry", "Thomas Tanghus", "J\u00f6rn Friedrich Dreyer", "Bart Visscher", "David Pr\u00e9vot", "root"], "commits": [34, 13, 10, 9, 8, 6, 5, 3, 3, 3], "id": [22, 16, 18, 27, 37, 148, 34, 33, 41, 31]}}