{"actions": 798, "added_lines": 32507.0, "added_lines_30": 1041655, "added_lines_365": 7047760, "added_lines_7": 136570, "authors": 21, "authors_30": 7, "authors_365": 17, "authors_7": 2, "avg_commits_author": 12.8095, "avg_commits_month": 7.6857, "avg_files_author": 15.7619, "avg_files_month": 9.4571, "branches": 7, "commits": 269, "commits_30": 51, "commits_365": 217, "commits_7": 3, "committers": 21, "diff_netadded_lines_30": 311244, "diff_netadded_lines_365": -4411083, "diff_netadded_lines_7": -333318, "diff_netauthors_30": 3, "diff_netauthors_365": 9, "diff_netauthors_7": -3, "diff_netcommits_30": 5, "diff_netcommits_365": 185, "diff_netcommits_7": -9, "diff_netfiles_30": 32, "diff_netfiles_365": 303, "diff_netfiles_7": -61, "diff_netremoved_lines_30": 374665, "diff_netremoved_lines_365": 448097, "diff_netremoved_lines_7": -312915, "files": 331, "files_30": 168, "files_365": 313, "files_7": 4, "first_date": "2010-01-12", "last_date": "2014-09-25", "percentage_added_lines_30": 42, "percentage_added_lines_365": 38, "percentage_added_lines_7": 70, "percentage_authors_30": 75, "percentage_authors_365": 112, "percentage_authors_7": 60, "percentage_commits_30": 10, "percentage_commits_365": 578, "percentage_commits_7": 75, "percentage_files_30": 23, "percentage_files_365": 3030, "percentage_files_7": 93, "percentage_removed_lines_30": 39, "percentage_removed_lines_365": 5, "percentage_removed_lines_7": 82, "removed_lines": 13146.0, "removed_lines_30": 1326201, "removed_lines_365": 8409433, "removed_lines_7": 66780, "repositories": 1}