{"actions": 807, "added_lines": 27698.0, "added_lines_30": 2474579, "added_lines_365": 10118970, "added_lines_7": 43783, "authors": 8, "authors_30": 4, "authors_365": 9, "authors_7": 1, "avg_commits_author": 28.88, "avg_commits_month": 23.1, "avg_files_author": 32.63, "avg_files_month": 26.1, "branches": 16, "commits": 231, "commits_30": 21, "commits_365": 234, "commits_7": 0, "committers": 8, "diff_netadded_lines_30": 688184, "diff_netadded_lines_365": -1430453, "diff_netadded_lines_7": -2031311, "diff_netauthors_30": 0, "diff_netauthors_365": 9, "diff_netauthors_7": -3, "diff_netcommits_30": 13, "diff_netcommits_365": 234, "diff_netcommits_7": -6, "diff_netfiles_30": 54, "diff_netfiles_365": 282, "diff_netfiles_7": -15, "diff_netremoved_lines_30": -23637, "diff_netremoved_lines_365": 4262728, "diff_netremoved_lines_7": 1501244, "files": 261, "files_30": 61, "files_365": 282, "files_7": 0, "first_date": "2010-01-12", "last_date": "2014-12-07", "percentage_added_lines_30": 38, "percentage_added_lines_365": 12, "percentage_added_lines_7": 97, "percentage_authors_30": 0, "percentage_authors_365": 0, "percentage_authors_7": 75, "percentage_commits_30": 162, "percentage_commits_365": 0, "percentage_commits_7": 100, "percentage_files_30": 771, "percentage_files_365": 0, "percentage_files_7": 100, "percentage_removed_lines_30": 1, "percentage_removed_lines_365": 58, "percentage_removed_lines_7": 1303, "removed_lines": 14257.0, "removed_lines_30": 1835365, "removed_lines_365": 11589622, "removed_lines_7": 1616378, "repositories": 1}