{"actions": 3015, "added_lines": 52836.0, "added_lines_30": 650948, "added_lines_365": 7182375, "added_lines_7": 66217, "authors": 1, "authors_30": 1, "authors_365": 1, "authors_7": 1, "avg_commits_author": 1784.0, "avg_commits_month": 43.5122, "avg_files_author": 1023.0, "avg_files_month": 24.9512, "branches": 81, "commits": 1784, "commits_30": 37, "commits_365": 579, "commits_7": 19, "committers": 1, "diff_netadded_lines_30": -370970, "diff_netadded_lines_365": -4190936, "diff_netadded_lines_7": -218503, "diff_netauthors_30": 0, "diff_netauthors_365": 0, "diff_netauthors_7": 0, "diff_netcommits_30": -25, "diff_netcommits_365": 169, "diff_netcommits_7": 14, "diff_netfiles_30": -27, "diff_netfiles_365": 293, "diff_netfiles_7": 7, "diff_netremoved_lines_30": -1041109, "diff_netremoved_lines_365": 704933, "diff_netremoved_lines_7": -178326, "files": 1023, "files_30": 45, "files_365": 537, "files_7": 17, "first_date": "2010-01-12", "last_date": "2014-10-14", "percentage_added_lines_30": 36, "percentage_added_lines_365": 36, "percentage_added_lines_7": 76, "percentage_authors_30": 0, "percentage_authors_365": 0, "percentage_authors_7": 0, "percentage_commits_30": 40, "percentage_commits_365": 41, "percentage_commits_7": 280, "percentage_files_30": 37, "percentage_files_365": 120, "percentage_files_7": 70, "percentage_removed_lines_30": 73, "percentage_removed_lines_365": 9, "percentage_removed_lines_7": 89, "removed_lines": 15447.0, "removed_lines_30": 367176, "removed_lines_365": 8473868, "removed_lines_7": 20862, "repositories": 7}