{"actions": 3467, "added_lines": 63686.0, "added_lines_30": 267967, "added_lines_365": 10774430, "added_lines_7": 13486, "authors": 1, "authors_30": 1, "authors_365": 1, "authors_7": 0, "avg_commits_author": 1922.0, "avg_commits_month": 43.68, "avg_files_author": 1287.0, "avg_files_month": 29.25, "branches": 105, "commits": 1716, "commits_30": 58, "commits_365": 581, "commits_7": 0, "committers": 1, "diff_netadded_lines_30": -2957136, "diff_netadded_lines_365": -918857, "diff_netadded_lines_7": -43938, "diff_netauthors_30": 0, "diff_netauthors_365": 0, "diff_netauthors_7": -1, "diff_netcommits_30": 12, "diff_netcommits_365": 141, "diff_netcommits_7": -9, "diff_netfiles_30": 156, "diff_netfiles_365": 422, "diff_netfiles_7": -70, "diff_netremoved_lines_30": 1299990, "diff_netremoved_lines_365": 4106537, "diff_netremoved_lines_7": -26548, "files": 1287, "files_30": 200, "files_365": 712, "files_7": 0, "first_date": "2010-01-12", "last_date": "2014-12-31", "percentage_added_lines_30": 91, "percentage_added_lines_365": 7, "percentage_added_lines_7": 76, "percentage_authors_30": 0, "percentage_authors_365": 0, "percentage_authors_7": 100, "percentage_commits_30": 26, "percentage_commits_365": 32, "percentage_commits_7": 100, "percentage_files_30": 354, "percentage_files_365": 145, "percentage_files_7": 100, "percentage_removed_lines_30": 282, "percentage_removed_lines_365": 53, "percentage_removed_lines_7": 87, "removed_lines": 19493.0, "removed_lines_30": 1759458, "removed_lines_365": 11726465, "removed_lines_7": 3914, "repositories": 7}