{"actions": 181418, "added_lines": 5199176.0, "added_lines_30": 1969541, "added_lines_365": 10783335, "added_lines_7": 36962, "authors": 360, "authors_30": 38, "authors_365": 178, "authors_7": 14, "avg_commits_author": 66.71, "avg_commits_month": 420.18, "avg_files_author": 154.85, "avg_files_month": 975.28, "branches": 746, "commits": 23950, "commits_30": 999, "commits_365": 8616, "commits_7": 70, "committers": 360, "diff_netadded_lines_30": 235874, "diff_netadded_lines_365": -952777, "diff_netadded_lines_7": -91108, "diff_netauthors_30": 2, "diff_netauthors_365": 62, "diff_netauthors_7": -5, "diff_netcommits_30": 124, "diff_netcommits_365": 1395, "diff_netcommits_7": -211, "diff_netfiles_30": -8003, "diff_netfiles_365": 35437, "diff_netfiles_7": -1768, "diff_netremoved_lines_30": 1004389, "diff_netremoved_lines_365": 4613526, "diff_netremoved_lines_7": -63654, "files": 55591, "files_30": 4930, "files_365": 51834, "files_7": 357, "first_date": "2010-01-12", "last_date": "2014-12-27", "percentage_added_lines_30": 13, "percentage_added_lines_365": 8, "percentage_added_lines_7": 71, "percentage_authors_30": 5, "percentage_authors_365": 53, "percentage_authors_7": 26, "percentage_commits_30": 14, "percentage_commits_365": 19, "percentage_commits_7": 75, "percentage_files_30": 61, "percentage_files_365": 216, "percentage_files_7": 83, "percentage_removed_lines_30": 118, "percentage_removed_lines_365": 62, "percentage_removed_lines_7": 77, "removed_lines": 4809561.0, "removed_lines_30": 1853574, "removed_lines_365": 11984145, "removed_lines_7": 18598, "repositories": 1}