{"actions": 4288, "added_lines": 121019.0, "added_lines_30": 598152, "added_lines_365": 7768499, "added_lines_7": 173685, "authors": 102, "authors_30": 15, "authors_365": 67, "authors_7": 8, "avg_commits_author": 14.1765, "avg_commits_month": 68.8571, "avg_files_author": 14.8922, "avg_files_month": 72.3333, "branches": 14, "commits": 1446, "commits_30": 66, "commits_365": 775, "commits_7": 24, "committers": 102, "diff_netadded_lines_30": 37153, "diff_netadded_lines_365": -3158538, "diff_netadded_lines_7": 57035, "diff_netauthors_30": 0, "diff_netauthors_365": 13, "diff_netauthors_7": 2, "diff_netcommits_30": -27, "diff_netcommits_365": 104, "diff_netcommits_7": 6, "diff_netfiles_30": 20, "diff_netfiles_365": 606, "diff_netfiles_7": -53, "diff_netremoved_lines_30": 265031, "diff_netremoved_lines_365": 113604, "diff_netremoved_lines_7": 380797, "files": 1519, "files_30": 162, "files_365": 1147, "files_7": 18, "first_date": "2010-01-12", "last_date": "2014-07-29", "percentage_added_lines_30": 6, "percentage_added_lines_365": 28, "percentage_added_lines_7": 48, "percentage_authors_30": 0, "percentage_authors_365": 24, "percentage_authors_7": 33, "percentage_commits_30": 29, "percentage_commits_365": 15, "percentage_commits_7": 33, "percentage_files_30": 14, "percentage_files_365": 112, "percentage_files_7": 74, "percentage_removed_lines_30": 57, "percentage_removed_lines_365": 1, "percentage_removed_lines_7": 611, "removed_lines": 72474.0, "removed_lines_30": 726553, "removed_lines_365": 8194569, "removed_lines_7": 443043, "repositories": 1}