{"authors.": {"authors": ["Bernhard Posselt", "Daniel Molkentin", "dietmaroc", "Volkan Gezer", "Randolph Carter", "blizzz", "j-ed", "Morris Jobke", "WireShout", "Thomas Mueller"], "commits": [395, 133, 127, 90, 59, 44, 44, 43, 42, 40], "id": [26, 15, 639, 10, 318, 64, 324, 18, 620, 22]}, "authors.last month": {"authors": ["Mark Barnard", "Volkan Gezer", "Daniel Molkentin", "Morris Jobke", "Bernhard Posselt", "Frank Karlitschek", "Tom Needham", "Andreas Fischer", "Craig Morrissey", "Javier Gonzalez"], "commits": [23, 12, 9, 8, 3, 3, 3, 1, 1, 1], "id": [133, 10, 15, 18, 26, 6, 8, 366, 469, 158]}, "authors.last year": {"authors": ["dietmaroc", "Volkan Gezer", "Bernhard Posselt", "Daniel Molkentin", "Randolph Carter", "Morris Jobke", "Thomas Mueller", "blizzz", "Mark Barnard", "Bj\u00f6rn Schie\u00dfle"], "commits": [124, 90, 78, 54, 48, 38, 38, 32, 23, 22], "id": [639, 10, 26, 15, 318, 18, 22, 64, 133, 32]}}