{"actions": 4385, "added_lines": 121806.0, "added_lines_30": 651128, "added_lines_365": 7064544, "added_lines_7": 61442, "authors": 109, "authors_30": 22, "authors_365": 71, "authors_7": 7, "avg_commits_author": 13.8426, "avg_commits_month": 71.1905, "avg_files_author": 14.4167, "avg_files_month": 74.1429, "branches": 25, "commits": 1495, "commits_30": 79, "commits_365": 790, "commits_7": 19, "committers": 109, "diff_netadded_lines_30": 8263, "diff_netadded_lines_365": -4659707, "diff_netadded_lines_7": 16745, "diff_netauthors_30": 8, "diff_netauthors_365": 15, "diff_netauthors_7": -2, "diff_netcommits_30": 17, "diff_netcommits_365": 85, "diff_netcommits_7": 3, "diff_netfiles_30": -39, "diff_netfiles_365": 639, "diff_netfiles_7": -9, "diff_netremoved_lines_30": 456426, "diff_netremoved_lines_365": -1094407, "diff_netremoved_lines_7": 31282, "files": 1557, "files_30": 126, "files_365": 1184, "files_7": 23, "first_date": "2010-01-12", "last_date": "2014-08-20", "percentage_added_lines_30": 1, "percentage_added_lines_365": 39, "percentage_added_lines_7": 37, "percentage_authors_30": 57, "percentage_authors_365": 26, "percentage_authors_7": 22, "percentage_commits_30": 27, "percentage_commits_365": 12, "percentage_commits_7": 18, "percentage_files_30": 23, "percentage_files_365": 117, "percentage_files_7": 28, "percentage_removed_lines_30": 112, "percentage_removed_lines_365": 12, "percentage_removed_lines_7": 118, "removed_lines": 72690.0, "removed_lines_30": 861886, "removed_lines_365": 7667273, "removed_lines_7": 57636, "repositories": 1}