{"actions": 553, "added_lines": 225461.0, "added_lines_30": 685871, "added_lines_365": 7325999, "added_lines_7": 218914, "authors": 18, "authors_30": 0, "authors_365": 9, "authors_7": 0, "avg_commits_author": 6.6471, "avg_commits_month": 3.5313, "avg_files_author": 12.2941, "avg_files_month": 6.5313, "branches": 3, "commits": 113, "commits_30": 0, "commits_365": 31, "commits_7": 0, "committers": 18, "diff_netadded_lines_30": -427437, "diff_netadded_lines_365": -3812078, "diff_netadded_lines_7": -53326, "diff_netauthors_30": -1, "diff_netauthors_365": 1, "diff_netauthors_7": 0, "diff_netcommits_30": -2, "diff_netcommits_365": -4, "diff_netcommits_7": 0, "diff_netfiles_30": -2, "diff_netfiles_365": 49, "diff_netfiles_7": 0, "diff_netremoved_lines_30": -1113766, "diff_netremoved_lines_365": 938179, "diff_netremoved_lines_7": -175850, "files": 209, "files_30": 0, "files_365": 127, "files_7": 0, "first_date": "2010-01-12", "last_date": "2014-10-17", "percentage_added_lines_30": 38, "percentage_added_lines_365": 34, "percentage_added_lines_7": 19, "percentage_authors_30": 100, "percentage_authors_365": 12, "percentage_authors_7": 0, "percentage_commits_30": 100, "percentage_commits_365": 11, "percentage_commits_7": 0, "percentage_files_30": 100, "percentage_files_365": 62, "percentage_files_7": 0, "percentage_removed_lines_30": 78, "percentage_removed_lines_365": 12, "percentage_removed_lines_7": 91, "removed_lines": 162707.0, "removed_lines_30": 308257, "removed_lines_365": 8387062, "removed_lines_7": 15719, "repositories": 1}