{"authors.": {"authors": ["Thomas Mueller", "Robin Appelman", "Jan-Christoph Borchardt", "libasys", "Lukas Reschke", "Vincent Petry", "Morris Jobke", "Georg Ehrke", "Joas Schilling", "J\u00f6rn Friedrich Dreyer"], "commits": [57, 52, 18, 8, 7, 6, 5, 4, 3, 3], "id": [22, 45, 13, 307, 16, 37, 18, 27, 49, 34]}, "authors.last month": {"authors": ["Robin Appelman", "Clark Tomlinson", "libasys", "Vincent Petry", "Volkan Gezer"], "commits": [7, 1, 1, 1, 1], "id": [45, 7529, 307, 37, 10]}, "authors.last year": {"authors": ["Thomas Mueller", "Robin Appelman", "Jan-Christoph Borchardt", "libasys", "Lukas Reschke", "Vincent Petry", "Morris Jobke", "Georg Ehrke", "Joas Schilling", "J\u00f6rn Friedrich Dreyer"], "commits": [57, 52, 18, 8, 7, 6, 5, 4, 3, 3], "id": [22, 45, 13, 307, 16, 37, 18, 27, 49, 34]}}