{"changed": 551, "changed_30": 59, "changed_365": 406, "changed_7": 17, "changers": 243, "changers_30": 57, "changers_365": 192, "changers_7": 15, "closed": 483, "closed_30": 28, "closed_365": 347, "closed_7": 5, "closers": 51, "closers_30": 11, "closers_365": 44, "closers_7": 3, "diff_netchanged_30": 35, "diff_netchanged_365": 232, "diff_netchanged_7": 7, "diff_netchangers_30": 30, "diff_netchangers_365": 103, "diff_netchangers_7": 2, "diff_netclosed_30": 17, "diff_netclosed_365": 207, "diff_netclosed_7": 3, "diff_netclosers_30": 1, "diff_netclosers_365": 35, "diff_netclosers_7": 1, "diff_netopened_30": 12, "diff_netopened_365": 247, "diff_netopened_7": 2, "diff_netopeners_30": 7, "diff_netopeners_365": 142, "diff_netopeners_7": 1, "first_date": "2013-05-06", "last_date": "2014-08-22", "opened": 613, "opened_30": 53, "opened_365": 430, "opened_7": 8, "openers": 271, "openers_30": 38, "openers_365": 214, "openers_7": 6, "percentage_changed_30": 145, "percentage_changed_365": 133, "percentage_changed_7": 70, "percentage_changers_30": 111, "percentage_changers_365": 115, "percentage_changers_7": 15, "percentage_closed_30": 154, "percentage_closed_365": 147, "percentage_closed_7": 150, "percentage_closers_30": 10, "percentage_closers_365": 388, "percentage_closers_7": 50, "percentage_opened_30": 29, "percentage_opened_365": 134, "percentage_opened_7": 33, "percentage_openers_30": 22, "percentage_openers_365": 197, "percentage_openers_7": 20, "trackers": 1}