{"closers.": {"closed": [453, 27, 11, 4, 3, 2, 2, 2, 2, 1], "closers": ["Raydiation", "cosenal", "jancborchardt", "MorrisJobke", "LukasReschke", "leonl42", "lunarok", "PVince81", "tanghus", "ares"], "id": [747, 1631, 733, 837, 1141, 853, 1801, 838, 1290, 1998]}, "closers.last month": {"closed": [20, 3], "closers": ["Raydiation", "cosenal"], "id": [747, 1631]}, "closers.last year": {"closed": [220, 19, 3, 2, 2, 2, 2, 1, 1, 1], "closers": ["Raydiation", "cosenal", "jancborchardt", "LukasReschke", "lunarok", "PVince81", "tanghus", "ares", "bastei", "Blaimi"], "id": [747, 1631, 733, 1141, 1801, 838, 1290, 1998, 1605, 2189]}}