{"changed": 11308, "changed_30": 703, "changed_365": 6817, "changed_7": 233, "changers": 2328, "changers_30": 180, "changers_365": 1468, "changers_7": 62, "closed": 9487, "closed_30": 273, "closed_365": 5061, "closed_7": 46, "closers": 598, "closers_30": 43, "closers_365": 357, "closers_7": 13, "diff_netchanged_30": -548, "diff_netchanged_365": 1648, "diff_netchanged_7": 88, "diff_netchangers_30": -107, "diff_netchangers_365": 357, "diff_netchangers_7": -10, "diff_netclosed_30": -197, "diff_netclosed_365": 604, "diff_netclosed_7": 14, "diff_netclosers_30": -24, "diff_netclosers_365": 64, "diff_netclosers_7": -4, "diff_netopened_30": -163, "diff_netopened_365": 839, "diff_netopened_7": 3, "diff_netopeners_30": -83, "diff_netopeners_365": 85, "diff_netopeners_7": -13, "first_date": "2012-08-25", "last_date": "2014-10-15", "opened": 11508, "opened_30": 460, "opened_365": 6156, "opened_7": 98, "openers": 3047, "openers_30": 184, "openers_365": 1677, "openers_7": 50, "percentage_changed_30": 43, "percentage_changed_365": 31, "percentage_changed_7": 60, "percentage_changers_30": 37, "percentage_changers_365": 32, "percentage_changers_7": 13, "percentage_closed_30": 41, "percentage_closed_365": 13, "percentage_closed_7": 43, "percentage_closers_30": 35, "percentage_closers_365": 21, "percentage_closers_7": 23, "percentage_opened_30": 26, "percentage_opened_365": 15, "percentage_opened_7": 3, "percentage_openers_30": 31, "percentage_openers_365": 5, "percentage_openers_7": 20, "trackers": 1}