{"senders.": {"id": [6, 37, 7979, 17, 12, 15, 7980, 22, 7866, 26], "senders": ["Frank Karlitschek", "Vincent Petry", "Jan-Christoph Borchardt", "Klaas Freitag", "Jos Poortvliet", "Daniel Molkentin", "Hoffmann, Patrick", "Thomas Mueller", "Aaron Boxer", "Bernhard Posselt"], "sent": [64, 56, 45, 36, 28, 25, 24, 17, 10, 10]}, "senders.last month": {"id": [6, 12, 7979, 7866, 17, 26, 7226, 37, 7974, 7288], "senders": ["Frank Karlitschek", "Jos Poortvliet", "Jan-Christoph Borchardt", "Aaron Boxer", "Klaas Freitag", "Bernhard Posselt", "Mark Ziegler", "Vincent Petry", "Chris", "Sudhir Khanger"], "sent": [22, 16, 11, 10, 9, 6, 6, 6, 5, 5]}, "senders.last year": {"id": [6, 37, 7979, 17, 12, 15, 7980, 22, 7866, 26], "senders": ["Frank Karlitschek", "Vincent Petry", "Jan-Christoph Borchardt", "Klaas Freitag", "Jos Poortvliet", "Daniel Molkentin", "Hoffmann, Patrick", "Thomas Mueller", "Aaron Boxer", "Bernhard Posselt"], "sent": [64, 56, 45, 36, 28, 25, 24, 17, 10, 10]}}