{"diff_netsenders_30": 10, "diff_netsenders_365": 169, "diff_netsenders_7": -9, "diff_netsent_30": 36, "diff_netsent_365": 611, "diff_netsent_7": 8, "first_date": "2012-10-12", "last_date": "2014-08-04", "percentage_senders_30": 21, "percentage_senders_365": 0, "percentage_senders_7": 39, "percentage_sent_30": 41, "percentage_sent_365": 0, "percentage_sent_7": 24, "repositories": 1, "senders": 169, "senders_30": 56, "senders_365": 169, "senders_7": 14, "senders_init": 98, "senders_response": 131, "sent": 611, "sent_30": 122, "sent_365": 611, "sent_7": 41, "sent_response": 434, "threads": 177}