{"closers.": {"closed": [116, 3, 2, 2, 2, 1, 1, 1, 1, 1], "closers": ["LEDfan", "stefan-niedermann", "fossxplorer", "jancborchardt", "Kondou-ger", "DeepDiver1975", "efinst0rm", "jacekjaros", "jbtbnl", "wakeup"], "id": [13788, 12212, 12310, 12127, 12711, 12189, 14838, 19048, 12708, 12521]}, "closers.last month": {"closed": [10, 1], "closers": ["LEDfan", "wakeup"], "id": [13788, 12521]}, "closers.last year": {"closed": [106, 3, 2, 2, 1, 1, 1, 1, 1], "closers": ["LEDfan", "stefan-niedermann", "fossxplorer", "jancborchardt", "DeepDiver1975", "efinst0rm", "jacekjaros", "jbtbnl", "wakeup"], "id": [13788, 12212, 12310, 12127, 12189, 14838, 19048, 12708, 12521]}}