{"closers.": {"closed": [853, 383, 206, 181, 139, 93, 27, 15, 12, 10], "closers": ["danimo", "dragotin", "ogoffart", "lmaestro", "guruz", "jancborchardt", "ckamm", "LukasReschke", "MTRichards", "DeepDiver1975"], "id": [12217, 12427, 12531, 12589, 12530, 12127, 19137, 12529, 12140, 12189]}, "closers.last month": {"closed": [20, 10, 8, 8, 6, 5, 4, 3, 1, 1], "closers": ["lmaestro", "guruz", "ckamm", "danimo", "dragotin", "kwillems", "ogoffart", "LukasReschke", "childnode", "christf"], "id": [12589, 12530, 19137, 12217, 12427, 12563, 12531, 12529, 12642, 20296]}, "closers.last year": {"closed": [306, 181, 151, 133, 131, 27, 22, 13, 9, 8], "closers": ["danimo", "lmaestro", "dragotin", "ogoffart", "guruz", "ckamm", "jancborchardt", "LukasReschke", "enoch85", "jnweiger"], "id": [12217, 12589, 12427, 12531, 12530, 19137, 12127, 12529, 12159, 12731]}}