{"changed": 551, "changed_30": 16, "changed_365": 300, "changed_7": 8, "changers": 139, "changers_30": 11, "changers_365": 83, "changers_7": 1, "closed": 515, "closed_30": 13, "closed_365": 272, "closed_7": 8, "closers": 38, "closers_30": 1, "closers_365": 27, "closers_7": 1, "diff_netchanged_30": 0, "diff_netchanged_365": 22, "diff_netchanged_7": 7, "diff_netchangers_30": 4, "diff_netchangers_365": 5, "diff_netchangers_7": 0, "diff_netclosed_30": 3, "diff_netclosed_365": 27, "diff_netclosed_7": 7, "diff_netclosers_30": 0, "diff_netclosers_365": 10, "diff_netclosers_7": 0, "diff_netopened_30": 0, "diff_netopened_365": -25, "diff_netopened_7": 6, "diff_netopeners_30": 0, "diff_netopeners_365": 15, "diff_netopeners_7": 6, "first_date": "2013-03-20", "last_date": "2014-07-29", "opened": 563, "opened_30": 14, "opened_365": 269, "opened_7": 7, "openers": 202, "openers_30": 14, "openers_365": 122, "openers_7": 7, "percentage_changed_30": 0, "percentage_changed_365": 7, "percentage_changed_7": 700, "percentage_changers_30": 57, "percentage_changers_365": 6, "percentage_changers_7": 0, "percentage_closed_30": 30, "percentage_closed_365": 11, "percentage_closed_7": 700, "percentage_closers_30": 0, "percentage_closers_365": 58, "percentage_closers_7": 0, "percentage_opened_30": 0, "percentage_opened_365": 8, "percentage_opened_7": 600, "percentage_openers_30": 0, "percentage_openers_365": 14, "percentage_openers_7": 600, "trackers": 1}