{"senders.": {"id": [15, 37, 11891, 17, 6, 7373, 7441, 11930, 7509, 11898], "senders": ["Daniel Molkentin", "Vincent Petry", "Chris", "Klaas Freitag", "Frank Karlitschek", "Emre Erenoglu", "Mark Ziegler", "Szl\u00e1dovics P\u00e9ter", "Sudhir Khanger", "Jan-Christoph Borchardt"], "sent": [49, 47, 45, 36, 28, 22, 21, 18, 17, 16]}, "senders.last month": {"id": [37, 7509, 11891, 12, 7649, 11927, 54, 6, 7400, 10252], "senders": ["Vincent Petry", "Sudhir Khanger", "Chris", "Jos Poortvliet", "Benjamin Seclier", "Pablo", "raghunayyar", "Frank Karlitschek", "Jakub Moscicki", "Leen de Braal"], "sent": [9, 8, 7, 6, 4, 4, 4, 3, 3, 3]}, "senders.last year": {"id": [15, 37, 11891, 17, 6, 7373, 7441, 11930, 7509, 11898], "senders": ["Daniel Molkentin", "Vincent Petry", "Chris", "Klaas Freitag", "Frank Karlitschek", "Emre Erenoglu", "Mark Ziegler", "Szl\u00e1dovics P\u00e9ter", "Sudhir Khanger", "Jan-Christoph Borchardt"], "sent": [49, 47, 45, 36, 28, 22, 21, 18, 17, 16]}}