{"diff_netsenders_30": -18, "diff_netsenders_365": 107, "diff_netsenders_7": -7, "diff_netsent_30": -107, "diff_netsent_365": 605, "diff_netsent_7": -8, "first_date": "2012-10-12", "last_date": "2014-09-17", "percentage_senders_30": 39, "percentage_senders_365": 10700, "percentage_senders_7": 70, "percentage_sent_30": 66, "percentage_sent_365": 60500, "percentage_sent_7": 61, "repositories": 1, "senders": 109, "senders_30": 28, "senders_365": 108, "senders_7": 3, "senders_init": 84, "senders_response": 74, "sent": 607, "sent_30": 55, "sent_365": 606, "sent_7": 5, "sent_response": 369, "threads": 238}