{"changed": 370, "changed_30": 32, "changed_365": 304, "changed_7": 6, "changers": 154, "changers_30": 22, "changers_365": 151, "changers_7": 5, "closed": 308, "closed_30": 21, "closed_365": 246, "closed_7": 3, "closers": 42, "closers_30": 6, "closers_365": 37, "closers_7": 2, "diff_netchanged_30": 8, "diff_netchanged_365": 221, "diff_netchanged_7": -8, "diff_netchangers_30": -4, "diff_netchangers_365": 132, "diff_netchangers_7": -2, "diff_netclosed_30": 10, "diff_netclosed_365": 183, "diff_netclosed_7": -3, "diff_netclosers_30": 3, "diff_netclosers_365": 28, "diff_netclosers_7": 0, "diff_netopened_30": 3, "diff_netopened_365": 200, "diff_netopened_7": -5, "diff_netopeners_30": -3, "diff_netopeners_365": 96, "diff_netopeners_7": -2, "first_date": "2013-08-27", "last_date": "2014-10-27", "opened": 386, "opened_30": 20, "opened_365": 293, "opened_7": 2, "openers": 114, "openers_30": 8, "openers_365": 110, "openers_7": 1, "percentage_changed_30": 33, "percentage_changed_365": 266, "percentage_changed_7": 57, "percentage_changers_30": 15, "percentage_changers_365": 694, "percentage_changers_7": 28, "percentage_closed_30": 90, "percentage_closed_365": 290, "percentage_closed_7": 50, "percentage_closers_30": 100, "percentage_closers_365": 311, "percentage_closers_7": 0, "percentage_opened_30": 17, "percentage_opened_365": 215, "percentage_opened_7": 71, "percentage_openers_30": 27, "percentage_openers_365": 685, "percentage_openers_7": 66, "trackers": 1}