{"closers.": {"closed": [2791, 2244, 1978, 1592, 1439, 1430, 1289, 1226, 870, 853], "closers": ["DeepDiver1975", "jancborchardt", "danimo", "MorrisJobke", "Raydiation", "PVince81", "LukasReschke", "karlitschek", "dragotin", "tanghus"], "id": [12189, 12127, 12217, 12225, 747, 12226, 12529, 12142, 12427, 12678]}, "closers.last month": {"closed": [95, 69, 63, 49, 34, 29, 25, 23, 22, 21], "closers": ["MorrisJobke", "carlaschroder", "DeepDiver1975", "LukasReschke", "nickvergessen", "Raydiation", "karlitschek", "jancborchardt", "LEDfan", "lmaestro"], "id": [12225, 18946, 12189, 12529, 12915, 747, 12142, 12127, 13788, 12589]}, "closers.last year": {"closed": [1340, 1157, 1038, 1028, 806, 764, 489, 470, 467, 366], "closers": ["DeepDiver1975", "PVince81", "MorrisJobke", "jancborchardt", "LukasReschke", "danimo", "lmaestro", "karlitschek", "Raydiation", "VicDeo"], "id": [12189, 12226, 12225, 12127, 12529, 12217, 12589, 12142, 747, 12374]}, "openers.": {"id": [12127, 12189, 12226, 12529, 12225, 12197, 12512, 12863, 12341, 12521], "opened": [1357, 1097, 1032, 569, 557, 548, 462, 451, 436, 410], "openers": ["jancborchardt", "DeepDiver1975", "PVince81", "LukasReschke", "MorrisJobke", "schiesbn", "ser72", "icewind1991", "butonic", "wakeup"]}, "openers.last month": {"id": [12225, 12529, 12915, 12189, 12127, 12226, 747, 18946, 13026, 12863], "opened": [60, 37, 33, 31, 29, 26, 23, 18, 16, 16], "openers": ["MorrisJobke", "LukasReschke", "nickvergessen", "DeepDiver1975", "jancborchardt", "PVince81", "Raydiation", "carlaschroder", "arkascha", "icewind1991"]}, "openers.last year": {"id": [12226, 12127, 12189, 12529, 12521, 12225, 12915, 12512, 12863, 12197], "opened": [743, 651, 578, 424, 391, 338, 297, 262, 245, 237], "openers": ["PVince81", "jancborchardt", "DeepDiver1975", "LukasReschke", "wakeup", "MorrisJobke", "nickvergessen", "ser72", "icewind1991", "schiesbn"]}}