{"allhistory_participants": 7084, "changed": 19817, "changed_30": 2162, "changed_365": 12797, "changed_7": 698, "changers": 3669, "changers_30": 530, "changers_365": 2450, "changers_7": 171, "closed": 16956, "closed_30": 1144, "closed_365": 10088, "closed_7": 270, "closers": 983, "closers_30": 129, "closers_365": 637, "closers_7": 52, "diff_netchanged_30": 378, "diff_netchanged_365": 4706, "diff_netchanged_7": 52, "diff_netchangers_30": 83, "diff_netchangers_365": 776, "diff_netchangers_7": -24, "diff_netclosed_30": 110, "diff_netclosed_365": 3129, "diff_netclosed_7": -23, "diff_netclosers_30": 17, "diff_netclosers_365": 184, "diff_netclosers_7": -2, "diff_netopened_30": 38, "diff_netopened_365": 3399, "diff_netopened_7": 75, "diff_netopeners_30": 54, "diff_netopeners_365": 560, "diff_netopeners_7": 17, "domains": 0, "first_date": "2012-08-25", "last_date": "2014-08-31", "opened": 20708, "opened_30": 1430, "opened_365": 12049, "opened_7": 376, "openers": 4527, "openers_30": 503, "openers_365": 2756, "openers_7": 156, "percentage_changed_30": 21, "percentage_changed_365": 58, "percentage_changed_7": 8, "percentage_changers_30": 18, "percentage_changers_365": 46, "percentage_changers_7": 12, "percentage_closed_30": 10, "percentage_closed_365": 44, "percentage_closed_7": 7, "percentage_closers_30": 15, "percentage_closers_365": 40, "percentage_closers_7": 3, "percentage_opened_30": 2, "percentage_opened_365": 39, "percentage_opened_7": 24, "percentage_openers_30": 12, "percentage_openers_365": 25, "percentage_openers_7": 12, "trackers": 52, "type": "github", "url": "https://api.github.com/repos/owncloud/android/issues"}