{"authors.": {"authors": ["Morris Jobke", "Volkan Gezer", "Thomas Mueller", "leizh", "J\u00f6rn Friedrich Dreyer", "Jan-Christoph Borchardt", "Bernhard Posselt", "Vincent Petry", "Xe\u0301fir Destiny", "Armin"], "commits": [261, 62, 25, 13, 12, 6, 2, 2, 2, 1], "id": [18, 10, 22, 482, 34, 13, 26, 37, 481, 484]}, "authors.last month": {"authors": ["Morris Jobke", "Volkan Gezer"], "commits": [41, 39], "id": [18, 10]}, "authors.last year": {"authors": ["Morris Jobke", "Volkan Gezer", "Thomas Mueller", "leizh", "J\u00f6rn Friedrich Dreyer", "Jan-Christoph Borchardt", "Bernhard Posselt", "Vincent Petry", "Xe\u0301fir Destiny", "Armin"], "commits": [243, 62, 25, 13, 12, 6, 2, 2, 2, 1], "id": [18, 10, 22, 482, 34, 13, 26, 37, 481, 484]}}