{"actions": 22436, "added_lines": 900272.0, "added_lines_30": 750420, "added_lines_365": 6602331, "added_lines_7": 40338, "authors": 43, "authors_30": 7, "authors_365": 21, "authors_7": 3, "avg_commits_author": 57.8293, "avg_commits_month": 84.6786, "avg_files_author": 133.7805, "avg_files_month": 195.8929, "branches": 6, "commits": 2371, "commits_30": 195, "commits_365": 1008, "commits_7": 35, "committers": 43, "diff_netadded_lines_30": -44141, "diff_netadded_lines_365": -4908982, "diff_netadded_lines_7": -295445, "diff_netauthors_30": 2, "diff_netauthors_365": -7, "diff_netauthors_7": 0, "diff_netcommits_30": 159, "diff_netcommits_365": -183, "diff_netcommits_7": 11, "diff_netfiles_30": 464, "diff_netfiles_365": 1330, "diff_netfiles_7": -259, "diff_netremoved_lines_30": 203809, "diff_netremoved_lines_365": -9067, "diff_netremoved_lines_7": -653548, "files": 5485, "files_30": 489, "files_365": 4230, "files_7": 52, "first_date": "2010-01-12", "last_date": "2014-09-10", "percentage_added_lines_30": 5, "percentage_added_lines_365": 42, "percentage_added_lines_7": 87, "percentage_authors_30": 40, "percentage_authors_365": 25, "percentage_authors_7": 0, "percentage_commits_30": 441, "percentage_commits_365": 15, "percentage_commits_7": 45, "percentage_files_30": 1855, "percentage_files_365": 45, "percentage_files_7": 83, "percentage_removed_lines_30": 22, "percentage_removed_lines_365": 0, "percentage_removed_lines_7": 87, "removed_lines": 807752.0, "removed_lines_30": 1121028, "removed_lines_365": 8042929, "removed_lines_7": 90945, "repositories": 1}