{"actions": 522, "added_lines": 28945.0, "added_lines_30": 803128, "added_lines_365": 7039310, "added_lines_7": 109266, "authors": 2, "authors_30": 1, "authors_365": 2, "authors_7": 1, "avg_commits_author": 54.5, "avg_commits_month": 13.625, "avg_files_author": 77.5, "avg_files_month": 19.375, "branches": 1, "commits": 109, "commits_30": 6, "commits_365": 109, "commits_7": 3, "committers": 2, "diff_netadded_lines_30": -67092, "diff_netadded_lines_365": -4394187, "diff_netadded_lines_7": -90555, "diff_netauthors_30": 0, "diff_netauthors_365": 2, "diff_netauthors_7": 0, "diff_netcommits_30": 0, "diff_netcommits_365": 109, "diff_netcommits_7": 0, "diff_netfiles_30": 33, "diff_netfiles_365": 155, "diff_netfiles_7": -31, "diff_netremoved_lines_30": 581876, "diff_netremoved_lines_365": 453402, "diff_netremoved_lines_7": -72040, "files": 155, "files_30": 43, "files_365": 155, "files_7": 6, "first_date": "2010-01-12", "last_date": "2014-09-27", "percentage_added_lines_30": 7, "percentage_added_lines_365": 38, "percentage_added_lines_7": 45, "percentage_authors_30": 0, "percentage_authors_365": 0, "percentage_authors_7": 0, "percentage_commits_30": 0, "percentage_commits_365": 0, "percentage_commits_7": 0, "percentage_files_30": 330, "percentage_files_365": 0, "percentage_files_7": 83, "percentage_removed_lines_30": 89, "percentage_removed_lines_365": 5, "percentage_removed_lines_7": 60, "removed_lines": 4280.0, "removed_lines_30": 1233250, "removed_lines_365": 8401977, "removed_lines_7": 47530, "repositories": 1}