{"actions": 496559, "added_lines": 15684690.0, "added_lines_30": 1984866, "added_lines_365": 10779015, "added_lines_7": 50998, "authors": 33, "authors_30": 22, "authors_365": 29, "authors_7": 19, "avg_commits_author": 1317.5, "avg_commits_month": 739.65, "avg_files_author": 3620.16, "avg_files_month": 2032.37, "branches": 1020, "commits": 34391, "commits_30": 1287, "commits_365": 13699, "commits_7": 160, "committers": 33, "diff_netadded_lines_30": 123900, "diff_netadded_lines_365": -1001273, "diff_netadded_lines_7": -84625, "diff_netauthors_30": 0, "diff_netauthors_365": 5, "diff_netauthors_7": 0, "diff_netcommits_30": 209, "diff_netcommits_365": 2365, "diff_netcommits_7": -123, "diff_netfiles_30": -16713, "diff_netfiles_365": 17325, "diff_netfiles_7": -600, "diff_netremoved_lines_30": 112156, "diff_netremoved_lines_365": 4582480, "diff_netremoved_lines_7": -71383, "files": 115845, "files_30": 3104, "files_365": 58449, "files_7": 476, "first_date": "2010-01-12", "last_date": "2014-12-25", "percentage_added_lines_30": 6, "percentage_added_lines_365": 8, "percentage_added_lines_7": 62, "percentage_authors_30": 0, "percentage_authors_365": 20, "percentage_authors_7": 0, "percentage_commits_30": 19, "percentage_commits_365": 20, "percentage_commits_7": 43, "percentage_files_30": 84, "percentage_files_365": 42, "percentage_files_7": 55, "percentage_removed_lines_30": 6, "percentage_removed_lines_365": 61, "percentage_removed_lines_7": 73, "removed_lines": 14434290.0, "removed_lines_30": 1866485, "removed_lines_365": 11984294, "removed_lines_7": 25158, "repositories": 56}