{"authors.": {"authors": ["Thomas Mueller", "Thomas Tanghus", "Klaas Freitag", "Bernhard Posselt", "Robin Appelman", "Georg Ehrke", "Daniel Molkentin", "Bj\u00f6rn Schie\u00dfle", "Bart Visscher", "Jan-Christoph Borchardt"], "commits": [8860.0, 6208.0, 5045.0, 3931.0, 3489.0, 3248.0, 2631.0, 2629.0, 2514.0, 2051.0], "id": [22, 148, 17, 26, 45, 27, 15, 32, 33, 13]}, "authors.last month": {"authors": ["Morris Jobke", "Robin Appelman", "Bernhard Posselt", "Joas Schilling", "Lukas Reschke", "Thomas Mueller", "Vincent Petry", "Bj\u00f6rn Schie\u00dfle", "LEDfan", "Jan-Christoph Borchardt"], "commits": [190.0, 156.0, 149.0, 130.0, 114.0, 109.0, 103.0, 73.0, 71.0, 68.0], "id": [18, 45, 26, 49, 16, 22, 37, 32, 454, 13]}, "authors.last year": {"authors": ["Thomas Mueller", "Bernhard Posselt", "Robin Appelman", "Klaas Freitag", "Olivier Goffart", "Vincent Petry", "Jan-Christoph Borchardt", "Daniel Molkentin", "Lukas Reschke", "Morris Jobke"], "commits": [2688.0, 1303.0, 1274.0, 1140.0, 1074.0, 982.0, 949.0, 930.0, 889.0, 883.0], "id": [22, 26, 45, 17, 107, 37, 13, 15, 16, 18]}}