{"actions": 613495, "added_lines": 24942950.0, "added_lines_30": 950279, "added_lines_365": 7664426, "added_lines_7": 394618, "authors": 629, "authors_30": 77, "authors_365": 342, "authors_7": 44, "avg_commits_author": 107.5707, "avg_commits_month": 1173.8421, "avg_files_author": 231.3248, "avg_files_month": 2524.2807, "branches": 934, "commits": 66909, "commits_30": 2331, "commits_365": 25267, "commits_7": 587, "committers": 629, "core": 26, "diff_netadded_lines_30": -53988, "diff_netadded_lines_365": -3344977, "diff_netadded_lines_7": 187139, "diff_netauthors_30": -30, "diff_netauthors_365": 82, "diff_netauthors_7": 1, "diff_netcommits_30": -303, "diff_netcommits_365": 2196, "diff_netcommits_7": 38, "diff_netfiles_30": -1579, "diff_netfiles_365": 26804, "diff_netfiles_7": 6256, "diff_netremoved_lines_30": -869062, "diff_netremoved_lines_365": 1180299, "diff_netremoved_lines_7": 178072, "domains": 433, "files": 143884, "files_30": 12575, "files_365": 88928, "files_7": 8244, "first_date": "2010-01-12", "last_date": "2014-10-26", "occasional": 549, "percentage_added_lines_30": 5, "percentage_added_lines_365": 30, "percentage_added_lines_7": 90, "percentage_authors_30": 28, "percentage_authors_365": 31, "percentage_authors_7": 2, "percentage_commits_30": 11, "percentage_commits_365": 9, "percentage_commits_7": 6, "percentage_files_30": 11, "percentage_files_365": 43, "percentage_files_7": 314, "percentage_removed_lines_30": 66, "percentage_removed_lines_365": 16, "percentage_removed_lines_7": 960, "regular": 52, "removed_lines": 20257448.0, "removed_lines_30": 435786, "removed_lines_365": 8540347, "removed_lines_7": 196617, "repositories": 60, "type": "git", "url": "https://github.com/owncloud/test"}