{"actions": 864, "added_lines": 17122.0, "added_lines_30": 913902, "added_lines_365": 7484278, "added_lines_7": 332040, "authors": 5, "authors_30": 0, "authors_365": 4, "authors_7": 0, "avg_commits_author": 10.8, "avg_commits_month": 13.5, "avg_files_author": 67.4, "avg_files_month": 84.25, "branches": 2, "commits": 54, "commits_30": 0, "commits_365": 14, "commits_7": 0, "committers": 5, "diff_netadded_lines_30": 193354, "diff_netadded_lines_365": -3180843, "diff_netadded_lines_7": 128769, "diff_netauthors_30": 0, "diff_netauthors_365": 2, "diff_netauthors_7": 0, "diff_netcommits_30": 0, "diff_netcommits_365": -26, "diff_netcommits_7": 0, "diff_netfiles_30": 0, "diff_netfiles_365": -141, "diff_netfiles_7": 0, "diff_netremoved_lines_30": 537847, "diff_netremoved_lines_365": 973827, "diff_netremoved_lines_7": 592326, "files": 337, "files_30": 0, "files_365": 158, "files_7": 0, "first_date": "2010-01-12", "last_date": "2014-09-03", "percentage_added_lines_30": 26, "percentage_added_lines_365": 29, "percentage_added_lines_7": 63, "percentage_authors_30": 0, "percentage_authors_365": 100, "percentage_authors_7": 0, "percentage_commits_30": 0, "percentage_commits_365": 65, "percentage_commits_7": 0, "percentage_files_30": 0, "percentage_files_365": 47, "percentage_files_7": 0, "percentage_removed_lines_30": 71, "percentage_removed_lines_365": 12, "percentage_removed_lines_7": 389, "removed_lines": 4533.0, "removed_lines_30": 1295368, "removed_lines_365": 8517274, "removed_lines_7": 744401, "repositories": 1}